{
    "stats_90_day_close_price": {
        "min": 1332.5,
        "max": 1519.3,
        "mean": 1431.22
    },
    "stats_vwap_by_month": {
        "2017-5": 1126.62,
        "2017-6": 1145.1,
        "2017-7": 1142.3,
        "2017-8": 1148.01,
        "2017-9": 1205.45,
        "2017-10": 1183.22,
        "2017-11": 1167.11,
        "2017-12": 1132.24,
        "2018-1": 1165.94,
        "2018-2": 1125.11,
        "2018-3": 1122.69,
        "2018-4": 1162.55,
        "2018-5": 1272.87,
        "2018-6": 1272.96,
        "2018-7": 1389.88,
        "2018-8": 1405.94,
        "2018-9": 1301.42,
        "2018-10": 1200.93,
        "2018-11": 1306.45,
        "2018-12": 1358.38,
        "2019-1": 1397.08,
        "2019-2": 1421.09,
        "2019-3": 1444.56,
        "2019-4": 1460.55,
        "2019-5": 1374.92
    },
    "stats_average_price": {
        "1 week": 1360.25,
        "2 weeks": 1394.71,
        "1 month": 1419.62,
        "2 months": 1447.06,
        "6 months": 1400.6,
        "1 year": 1356.3
    },
    "stats_profit_loss_percentage": {
        "1 week": -4.15,
        "2 weeks": -9.8,
        "1 month": -7.43,
        "2 months": -7.67,
        "6 months": 3.57,
        "1 year": 2.64
    },
    "stats_quantity_trend": {
        "Slight": {
            "mean": 1012164.96,
            "median": 840293.0
        }
    }
}